Workbook
Name Aporte: Planilha1!$G$21
Name Rendimeoto_carteira: Planilha1!$G$16
Name sugestão_investimento: Planilha1!$G$17

Sheet Planilha1
B14: CONFIGURAÇÕES
B15: Salário | G15: 3000
B16: Rendimento Carteira | G16: 0.006
B17: Sugestão de Investimento | G17: =G15*30% -> 900
B20: INVESTIMENTO MENSAL
B21: Quanto investir por mês? | G21: 900
B22: Por quantos anos? | G22: 10
B23: Taxa de rendimento mensal? | G23: 0.01079
B24: Patrimônio acumulado? | G24: =FV(G23,G22*12,G21*-1) -> 218955.79
B25: Dividendos mensais? | G25: =G24*G23 -> 2362.533
B28: Cenários | G28: Dividendos
A29: 2 | B29: Quanto em 2 Anos? | D29: =FV($G$23,$A29*12,$G$21*-1) -> 24504.865 | G29: =D29*Rendimeoto_carteira -> 147.02919
A30: 5 | B30: Quanto em 5 Anos? | D30: =FV($G$23,$A30*12,$G$21*-1) -> 75399.223 | G30: =D30*Rendimeoto_carteira -> 452.39534
A31: 10 | B31: Quanto em 10 Anos? | D31: =FV($G$23,$A31*12,$G$21*-1) -> 218955.79 | G31: =D31*Rendimeoto_carteira -> 1313.7347
A32: 20 | B32: Quanto em 20 Anos? | D32: =FV($G$23,$A32*12,$G$21*-1) -> 1012678.6 | G32: =D32*Rendimeoto_carteira -> 6076.0714
A33: 30 | B33: Quanto em 30 Anos? | D33: =FV($G$23,$A33*12,$G$21*-1) -> 3889952.7 | G33: =D33*Rendimeoto_carteira -> 23339.716
B36: Perfil | D36: Moderado
B37: VALOR A SER ENVESTIDO POR MÊS | D37: =Aporte -> 900
B40: TIPO DE FII | D40: Percentual Sugerido | G40: Valores
B41: PAPEL | D41: =VLOOKUP($D$36&"-"&B41,Planilha2!$B$1:$F$19,5,FALSE) -> 0.32 | G41: =D41*$D$37 -> 288
B42: TIJOLO | D42: =VLOOKUP($D$36&"-"&B42,Planilha2!$B$1:$F$19,5,FALSE) -> 0.3 | G42: =D42*$D$37 -> 270
B43: HÍBRIDOS | D43: =VLOOKUP($D$36&"-"&B43,Planilha2!$B$1:$F$19,5,FALSE) -> 0.08 | G43: =D43*$D$37 -> 72
B44: FOFs | D44: =VLOOKUP($D$36&"-"&B44,Planilha2!$B$1:$F$19,5,FALSE) -> 0.1 | G44: =D44*$D$37 -> 90
B45: DESENVOLVIMENTO | D45: =VLOOKUP($D$36&"-"&B45,Planilha2!$B$1:$F$19,5,FALSE) -> 0.1 | G45: =D45*$D$37 -> 90
B46: HOTELARIAS | D46: =VLOOKUP($D$36&"-"&B46,Planilha2!$B$1:$F$19,5,FALSE) -> 0.1 | G46: =D46*$D$37 -> 90
B47: TOTAL | G47: =SUM(G41:G46) -> 900

Sheet Planilha2
B1: CHAVE | C1: PERFIL | D1: TIPOS DE FII | F1: %
B2: =C2&"-"&D2 -> Conservador-PAPEL | C2: Conservador | D2: PAPEL | F2: 0.3 | J2: %
B3: =C3&"-"&D3 -> Conservador-TIJOLO | C3: Conservador | D3: TIJOLO | F3: 0.5 | I3: Moderado-TIJOLO | J3: =VLOOKUP(I3,$B$1:$F$19,5,FALSE) -> 0.3
B4: =C4&"-"&D4 -> Conservador-HÍBRIDOS | C4: Conservador | D4: HÍBRIDOS | F4: 0.1
B5: =C5&"-"&D5 -> Conservador-FOFs | C5: Conservador | D5: FOFs | F5: 0.1
B6: =C6&"-"&D6 -> Conservador-DESENVOLVIMENTO | C6: Conservador | D6: DESENVOLVIMENTO | F6: 0
B7: =C7&"-"&D7 -> Conservador-HOTELARIAS | C7: Conservador | D7: HOTELARIAS | F7: 0
B8: =C8&"-"&D8 -> Moderado-PAPEL | C8: Moderado | D8: PAPEL | F8: 0.32
B9: =C9&"-"&D9 -> Moderado-TIJOLO | C9: Moderado | D9: TIJOLO | F9: 0.3
B10: =C10&"-"&D10 -> Moderado-HÍBRIDOS | C10: Moderado | D10: HÍBRIDOS | F10: 0.08
B11: =C11&"-"&D11 -> Moderado-FOFs | C11: Moderado | D11: FOFs | F11: 0.1
B12: =C12&"-"&D12 -> Moderado-DESENVOLVIMENTO | C12: Moderado | D12: DESENVOLVIMENTO | F12: 0.1
B13: =C13&"-"&D13 -> Moderado-HOTELARIAS | C13: Moderado | D13: HOTELARIAS | F13: 0.1
B14: =C14&"-"&D14 -> Agressivo-PAPEL | C14: Agressivo | D14: PAPEL | F14: 0.5
B15: =C15&"-"&D15 -> Agressivo-TIJOLO | C15: Agressivo | D15: TIJOLO | F15: 0.2
... B19: =C19&"-"&D19 -> Agressivo-HOTELARIAS | C19: Agressivo | D19: HOTELARIAS | F19: 0.1
